{"points":[{"ts":1777460028375,"intent_rank":14,"intent_to_amount_hr":7.964356,"best_to_amount_hr":10,"delta_hr":2.0356439999999996,"delta_bps":2035.6439999999996,"status":"ok","intent_tool":"lifiIntents","best_tool":"polymerStandard"},{"ts":1777546395888,"intent_rank":13,"intent_to_amount_hr":9.859752,"best_to_amount_hr":10,"delta_hr":0.1402479999999997,"delta_bps":140.2479999999997,"status":"ok","intent_tool":"lifiIntents","best_tool":"eco"},{"ts":1777630894140,"intent_rank":12,"intent_to_amount_hr":8.442995,"best_to_amount_hr":10,"delta_hr":1.5570050000000002,"delta_bps":1557.005,"status":"ok","intent_tool":"lifiIntents","best_tool":"eco"},{"ts":1777715830968,"intent_rank":14,"intent_to_amount_hr":9.845652,"best_to_amount_hr":10.000716,"delta_hr":0.1550640000000012,"delta_bps":155.05289821248917,"status":"ok","intent_tool":"lifiIntents","best_tool":"squid"},{"ts":1777802511073,"intent_rank":11,"intent_to_amount_hr":9.915395,"best_to_amount_hr":10,"delta_hr":0.08460499999999982,"delta_bps":84.60499999999982,"status":"ok","intent_tool":"lifiIntents","best_tool":"eco"},{"ts":1777892612303,"intent_rank":14,"intent_to_amount_hr":8.105739,"best_to_amount_hr":10.001065,"delta_hr":1.8953260000000007,"delta_bps":1895.1241692759727,"status":"ok","intent_tool":"lifiIntents","best_tool":"squid"},{"ts":1777977857743,"intent_rank":13,"intent_to_amount_hr":9.881641,"best_to_amount_hr":10.000042,"delta_hr":0.11840100000000042,"delta_bps":118.400502717889,"status":"ok","intent_tool":"lifiIntents","best_tool":"squid"}]}